himena_stats/__init__.py
himena_stats/_lazy_import.py
himena_stats/consts.py
himena_stats/distributions/__init__.py
himena_stats/distributions/_construct.py
himena_stats/distributions/_fit.py
himena_stats/distributions/_methods.py
himena_stats/distributions/_utils.py
himena_stats/distributions/_widget.py
himena_stats/io/__init__.py
himena_stats/io/_serialize.py
himena_stats/io/core.py
himena_stats/test_tools/__init__.py
himena_stats/test_tools/_goodness.py
himena_stats/test_tools/_multiple.py
himena_stats/test_tools/_single.py
himena_stats/test_tools/_utils.py
himena_stats-0.1.0.dist-info/METADATA
himena_stats-0.1.0.dist-info/WHEEL
himena_stats-0.1.0.dist-info/entry_points.txt
himena_stats-0.1.0.dist-info/licenses/LICENSE
himena_stats-0.1.0.dist-info/RECORD
