Metadata-Version: 2.4
Name: himena-stats
Version: 0.1.0
Summary: Statistical testing and modeling in himena.
Project-URL: Documentation, https://github.com/hanjinliu/himena-stats#readme
Project-URL: Issues, https://github.com/hanjinliu/himena-stats/issues
Project-URL: Source, https://github.com/hanjinliu/himena-stats
Author-email: hanjinliu <liuhanjin.sc@gmail.com>
License: BSD 3-Clause License
License-File: LICENSE
Classifier: Development Status :: 4 - Beta
Classifier: Programming Language :: Python
Classifier: Programming Language :: Python :: 3.10
Classifier: Programming Language :: Python :: 3.11
Classifier: Programming Language :: Python :: 3.12
Classifier: Programming Language :: Python :: 3.13
Classifier: Programming Language :: Python :: Implementation :: CPython
Classifier: Programming Language :: Python :: Implementation :: PyPy
Requires-Python: >=3.10
Requires-Dist: himena
Requires-Dist: numpy>=2.0
Requires-Dist: scikit-posthocs>=0.7.0
Requires-Dist: scipy>=1.10.0
Provides-Extra: testing
Requires-Dist: himena[testing]; extra == 'testing'
Requires-Dist: pyqt6; extra == 'testing'
Requires-Dist: pytest-cov>=3.0.0; extra == 'testing'
Requires-Dist: pytest>=6.0.0; extra == 'testing'
